[{"testmayfour":"deserunt consectetur Lorem incididunt","testmayfouragain":["in sed pariatur consectetu","ea deserunt","culpa","in Ut","deserunt Ut dolor ut pariatur"]},{"testmayfour":"consectetur amet do","testmayfouragain":["ad sunt labore officia dolore"]},{"testmayfour":"Ut quis cillum","testmayfouragain":["Lorem sed elit sit ut","officia laborum et voluptat","nulla culpa minim","ut laborum incid"]},{"testmayfour":"Ut","testmayfouragain":["do sunt exercitation","ea sed","irur","ut officia quis"]},{"testmayfour":"mollit et","testmayfouragain":["sint labore sit exercitation fugiat","ipsum occaecat minim amet","nulla cupidatat aliqua ea"]}]